setup.cfg
setup.py
Squeak.egg-info/PKG-INFO
Squeak.egg-info/SOURCES.txt
Squeak.egg-info/dependency_links.txt
Squeak.egg-info/requires.txt
Squeak.egg-info/top_level.txt
squeak/__init__.py
squeak/entropy.py
squeak/main.py