Metadata-Version: 1.1
Name: Squeak
Version: 0.2.0
Summary: Analyse mouse trajectory data.
Home-page: https://github.com/EoinTravers/Squeak
Author: Eoin Travers
Author-email: etravers01@qub.ac.uk
License: GPL
Platform: UNKNOWN
Classifier: Development Status :: 4 - Beta
Classifier: Environment :: Console
Classifier: Operating System :: Unix
Classifier: Programming Language :: Python :: 2
